exceptionlib/__init__.py
exceptionlib/core.py
exceptionlib-0.1.1.dist-info/licenses/LICENSE
exceptionlib-0.1.1.dist-info/METADATA
exceptionlib-0.1.1.dist-info/WHEEL
exceptionlib-0.1.1.dist-info/top_level.txt
exceptionlib-0.1.1.dist-info/RECORD
