Metadata-Version: 2.4
Name: exceptionlib
Version: 0.1.1
Summary: Easily customizing exceptions in any way you can think of!
Author: Aiden
License: MIT License
